main.py
tablebin/__init__.py
tablebin/conditions.py
tablebin/exceptions.py
tablebin/formatters.py
tablebin/row.py
tablebin/style.py
tablebin/tablebin.py
tablebin-1.1.2.dist-info/LICENSE
tablebin-1.1.2.dist-info/METADATA
tablebin-1.1.2.dist-info/WHEEL
tablebin-1.1.2.dist-info/top_level.txt
tablebin-1.1.2.dist-info/RECORD
