Metadata-Version: 2.1
Name: tablebin
Version: 1.1.2
Summary: A light weight python api for the table bin platform.
Author-email: boldrack <me@boldrack.dev>
License: MIT License
Project-URL: Homepage, https://github.com/boldrack/tablebin-python
Keywords: table,api
Classifier: License :: OSI Approved :: MIT License
Classifier: Programming Language :: Python
Classifier: Programming Language :: Python :: 3
Requires-Python: >=3.9
License-File: LICENSE
Requires-Dist: requests
Provides-Extra: dev
Requires-Dist: bumpver; extra == "dev"
Requires-Dist: pip-tools; extra == "dev"
Requires-Dist: pytest; extra == "dev"
